[
  {
    "name": "noOrg",
    "merchantCount": 4516
  },
  {
    "name": "einundzwanzig",
    "merchantCount": 1459
  },
  {
    "name": "2140-meetups",
    "merchantCount": 452
  },
  {
    "name": "plan-b-network",
    "merchantCount": 197
  },
  {
    "name": "decouvre-bitcoin",
    "merchantCount": 114
  },
  {
    "name": "dwadziescia-jeden",
    "merchantCount": 103
  },
  {
    "name": "plan-b-network, mi-primer-bitcoin",
    "merchantCount": 83
  },
  {
    "name": "",
    "merchantCount": 59
  },
  {
    "name": "bit-devs",
    "merchantCount": 55
  },
  {
    "name": "breizh-bitcoin",
    "merchantCount": 33
  },
  {
    "name": "mi-primer-bitcoin",
    "merchantCount": 16
  },
  {
    "name": "bitcoin-jamii",
    "merchantCount": 5
  },
  {
    "name": "bitcoin4india",
    "merchantCount": 4
  }
]
